samey/__init__.py
samey/samey.py
samey/samey_metrics.py
samey/samey_utils.py
samey-0.1.0.dist-info/licenses/LICENSE
samey-0.1.0.dist-info/METADATA
samey-0.1.0.dist-info/WHEEL
samey-0.1.0.dist-info/top_level.txt
samey-0.1.0.dist-info/RECORD
