Metadata-Version: 2.4
Name: samey
Version: 0.1.0
Summary: Dataset diversity scoring for synthetic instruction data
Author-email: Vadim Borisov <vadim@tabularis.ai>
License: MIT License
Project-URL: Homepage, https://github.com/tabularis-ai/samey
Keywords: diversity,nlp,dataset,sft,dpo,synthetic-data
Requires-Python: >=3.9
License-File: LICENSE
Requires-Dist: numpy
Requires-Dist: pandas
Requires-Dist: scikit-learn
Requires-Dist: sentence-transformers
Dynamic: license-file
